<?xml version="1.0" encoding="utf-8"?>
<Application>
  <Views Id="Views">
    <DetailView Id="CoSoSanXuatKinhDoanh_DetailView">
      <Layout Id="Layout">
        <LayoutGroup Id="Main">
          <LayoutGroup Id="SimpleEditors">
            <LayoutGroup Id="CoSoSanXuatKinhDoanh">
              <LayoutGroup Id="CoSoSanXuatKinhDoanh_col1">
                <LayoutItem Id="SoDienThoai" RelativeSize="20" Index="5" />
              </LayoutGroup>
              <LayoutGroup Id="CoSoSanXuatKinhDoanh_col2">
                <LayoutItem Id="NgayThamDinhNgayNhat" Removed="True" />
              </LayoutGroup>
            </LayoutGroup>
          </LayoutGroup>
        </LayoutGroup>
      </Layout>
    </DetailView>
  </Views>
</Application>